extra/__init__.py
extra/__main__.py
extra/client.py
extra/config.py
extra/decorators.py
extra/handler.py
extra/model.py
extra/routing.py
extra/server.py
extra/features/__init__.py
extra/features/cache.py
extra/features/cors.py
extra/features/local.py
extra/http/__init__.py
extra/http/api.py
extra/http/model.py
extra/http/parser.py
extra/http/processors.py
extra/http/status.py
extra/services/__init__.py
extra/services/files.py
extra/services/proxy.py
extra/utils/__init__.py
extra/utils/codec.py
extra/utils/collections.py
extra/utils/files.py
extra/utils/htmpl.py
extra/utils/io.py
extra/utils/json.py
extra/utils/limits.py
extra/utils/logging.py
extra/utils/primitives.py
extra/utils/shell.py
extra/utils/term.py
extra/utils/uri.py
extra_http-1.0.9.dist-info/licenses/LICENSE
extra_http-1.0.9.dist-info/METADATA
extra_http-1.0.9.dist-info/WHEEL
extra_http-1.0.9.dist-info/entry_points.txt
extra_http-1.0.9.dist-info/top_level.txt
extra_http-1.0.9.dist-info/RECORD
